odoo10_addon_stock_exclude_to_remove_lot-10.0.1.0.0.99.dev4-py3.8-nspkg.pth
odoo/addons/stock_exclude_to_remove_lot/README.rst
odoo/addons/stock_exclude_to_remove_lot/__init__.py
odoo/addons/stock_exclude_to_remove_lot/__manifest__.py
odoo/addons/stock_exclude_to_remove_lot/i18n/stock_exclude_to_remove_lot.pot
odoo/addons/stock_exclude_to_remove_lot/models/__init__.py
odoo/addons/stock_exclude_to_remove_lot/models/stock_picking_type.py
odoo/addons/stock_exclude_to_remove_lot/models/stock_production_lot.py
odoo/addons/stock_exclude_to_remove_lot/readme/CONTRIBUTORS.rst
odoo/addons/stock_exclude_to_remove_lot/readme/DESCRIPTION.rst
odoo/addons/stock_exclude_to_remove_lot/readme/USAGE.rst
odoo/addons/stock_exclude_to_remove_lot/static/description/icon.png
odoo/addons/stock_exclude_to_remove_lot/static/description/index.html
odoo/addons/stock_exclude_to_remove_lot/tests/__init__.py
odoo/addons/stock_exclude_to_remove_lot/tests/test_remove_lots.py
odoo/addons/stock_exclude_to_remove_lot/views/stock_picking_type.xml
odoo10_addon_stock_exclude_to_remove_lot-10.0.1.0.0.99.dev4.dist-info/METADATA
odoo10_addon_stock_exclude_to_remove_lot-10.0.1.0.0.99.dev4.dist-info/WHEEL
odoo10_addon_stock_exclude_to_remove_lot-10.0.1.0.0.99.dev4.dist-info/namespace_packages.txt
odoo10_addon_stock_exclude_to_remove_lot-10.0.1.0.0.99.dev4.dist-info/top_level.txt
odoo10_addon_stock_exclude_to_remove_lot-10.0.1.0.0.99.dev4.dist-info/RECORD
