Metadata-Version: 2.1
Name: odoo10-addon-stock-exclude-to-remove-lot
Version: 10.0.1.0.0.99.dev4
Summary: This modules allows to exclude lots based on their removal date
Home-page: https://github.com/OCA/stock-logistics-workflow
Author: ACSONE SA/NV,Odoo Community Association (OCA)
Author-email: support@odoo-community.org
License: AGPL-3
Platform: UNKNOWN
Classifier: Programming Language :: Python
Classifier: Framework :: Odoo
Classifier: Framework :: Odoo :: 10.0
Classifier: License :: OSI Approved :: GNU Affero General Public License v3
Classifier: Development Status :: 3 - Alpha
Requires-Python: ~=2.7
Requires-Dist: odoo <10.1dev,>=10.0
